reviewbot/__init__.py
reviewbot/celery.py
reviewbot/config.py
reviewbot/deprecation.py
reviewbot/errors.py
reviewbot/main.py
reviewbot/repositories.py
reviewbot/tasks.py
reviewbot/processing/__init__.py
reviewbot/processing/review.py
reviewbot/processing/tests/__init__.py
reviewbot/processing/tests/test_file.py
reviewbot/processing/tests/test_review.py
reviewbot/testing/__init__.py
reviewbot/testing/testcases.py
reviewbot/testing/utils.py
reviewbot/tests/__init__.py
reviewbot/tests/test_celery.py
reviewbot/tests/test_config.py
reviewbot/tests/test_repositories.py
reviewbot/tests/test_tasks.py
reviewbot/tools/__init__.py
reviewbot/tools/cargotool.py
reviewbot/tools/checkstyle.py
reviewbot/tools/clang.py
reviewbot/tools/cppcheck.py
reviewbot/tools/cpplint.py
reviewbot/tools/doc8.py
reviewbot/tools/fbinfer.py
reviewbot/tools/flake8.py
reviewbot/tools/gofmt.py
reviewbot/tools/gotool.py
reviewbot/tools/jshint.py
reviewbot/tools/pmd.py
reviewbot/tools/pycodestyle.py
reviewbot/tools/pydocstyle.py
reviewbot/tools/pyflakes.py
reviewbot/tools/rbsecretscanner.py
reviewbot/tools/rubocop.py
reviewbot/tools/rustfmt.py
reviewbot/tools/shellcheck.py
reviewbot/tools/base/__init__.py
reviewbot/tools/base/mixins.py
reviewbot/tools/base/registry.py
reviewbot/tools/base/tool.py
reviewbot/tools/support/js/jshint_reporter.js
reviewbot/tools/testing/__init__.py
reviewbot/tools/testing/decorators.py
reviewbot/tools/testing/testcases.py
reviewbot/tools/tests/__init__.py
reviewbot/tools/tests/test_base_tool.py
reviewbot/tools/tests/test_cargotool.py
reviewbot/tools/tests/test_checkstyle.py
reviewbot/tools/tests/test_clang.py
reviewbot/tools/tests/test_cppcheck.py
reviewbot/tools/tests/test_cpplint.py
reviewbot/tools/tests/test_doc8.py
reviewbot/tools/tests/test_fbinfer.py
reviewbot/tools/tests/test_file_patterns_from_setting_mixin.py
reviewbot/tools/tests/test_flake8.py
reviewbot/tools/tests/test_gofmt.py
reviewbot/tools/tests/test_gotool.py
reviewbot/tools/tests/test_java_tool_mixin.py
reviewbot_worker-4.0.dist-info/METADATA
reviewbot_worker-4.0.dist-info/WHEEL
reviewbot_worker-4.0.dist-info/entry_points.txt
reviewbot_worker-4.0.dist-info/top_level.txt
reviewbot_worker-4.0.dist-info/RECORD
