Metadata-Version: 2.1
Name: reviewbot-worker
Version: 4.0
Summary: Review Bot, the automated code reviewer (worker)
Author: Beanbag, Inc.
Author-email: support@beanbaginc.com
Maintainer: Beanbag, Inc.
Maintainer-email: support@beanbaginc.com
License: MIT
Classifier: Development Status :: 5 - Production/Stable
Classifier: Environment :: Console
Classifier: Framework :: Review Board
Classifier: Intended Audience :: Developers
Classifier: License :: OSI Approved :: MIT License
Classifier: Operating System :: OS Independent
Classifier: Programming Language :: Python
Classifier: Programming Language :: Python :: 3
Classifier: Programming Language :: Python :: 3.8
Classifier: Programming Language :: Python :: 3.9
Classifier: Programming Language :: Python :: 3.10
Classifier: Programming Language :: Python :: 3.11
Classifier: Programming Language :: Python :: 3.12
Classifier: Topic :: Software Development
Classifier: Topic :: Software Development :: Quality Assurance
Requires-Python: >=3.8
Requires-Dist: appdirs >=1.4.4
Requires-Dist: celery ~=5.3
Requires-Dist: RBTools <6,>=4.0
Requires-Dist: flake8-json >=21.1
Provides-Extra: all
Requires-Dist: cpplint >=1.6 ; extra == 'all'
Requires-Dist: doc8 >=0.10.1 ; extra == 'all'
Requires-Dist: flake8 >=4.0 ; extra == 'all'
Requires-Dist: pycodestyle >=2.8 ; extra == 'all'
Requires-Dist: pydocstyle >=6.1.1 ; extra == 'all'
Requires-Dist: pyflakes >=2.4 ; extra == 'all'
